Metadata-Version: 2.1
Name: castleamongthestars
Version: 1.0.45
Summary: A system
Home-page: UNKNOWN
Author: Xtev
License: UNKNOWN
Platform: UNKNOWN
